{
  "lung_editable": [
    [
      {
        "x": 222.0,
        "y": 341.0
      },
      {
        "x": 214.0,
        "y": 341.0
      },
      {
        "x": 193.0,
        "y": 322.0
      },
      {
        "x": 183.0,
        "y": 282.0
      },
      {
        "x": 195.0,
        "y": 264.0
      },
      {
        "x": 195.0,
        "y": 252.0
      },
      {
        "x": 228.0,
        "y": 231.0
      },
      {
        "x": 253.0,
        "y": 240.0
      },
      {
        "x": 235.0,
        "y": 260.0
      },
      {
        "x": 229.0,
        "y": 286.0
      },
      {
        "x": 222.0,
        "y": 287.0
      },
      {
        "x": 214.0,
        "y": 275.0
      },
      {
        "x": 203.0,
        "y": 290.0
      },
      {
        "x": 230.0,
        "y": 295.0
      },
      {
        "x": 249.0,
        "y": 318.0
      },
      {
        "x": 236.0,
        "y": 335.0
      },
      {
        "x": 222.0,
        "y": 341.0
      }
    ],
    [
      {
        "x": 308.0,
        "y": 345.0
      },
      {
        "x": 292.0,
        "y": 341.0
      },
      {
        "x": 281.0,
        "y": 330.0
      },
      {
        "x": 309.0,
        "y": 308.0
      },
      {
        "x": 315.0,
        "y": 288.0
      },
      {
        "x": 313.0,
        "y": 270.0
      },
      {
        "x": 297.0,
        "y": 256.0
      },
      {
        "x": 294.0,
        "y": 237.0
      },
      {
        "x": 308.0,
        "y": 241.0
      },
      {
        "x": 313.0,
        "y": 256.0
      },
      {
        "x": 335.0,
        "y": 276.0
      },
      {
        "x": 321.0,
        "y": 288.0
      },
      {
        "x": 331.0,
        "y": 326.0
      },
      {
        "x": 308.0,
        "y": 345.0
      }
    ],
    [
      {
        "x": 213.0,
        "y": 262.0
      },
      {
        "x": 210.0,
        "y": 257.0
      },
      {
        "x": 197.0,
        "y": 260.0
      },
      {
        "x": 213.0,
        "y": 262.0
      }
    ],
    [
      {
        "x": 260.0,
        "y": 299.0
      },
      {
        "x": 251.0,
        "y": 296.0
      },
      {
        "x": 260.0,
        "y": 293.0
      },
      {
        "x": 260.0,
        "y": 299.0
      }
    ],
    [
      {
        "x": 96.0,
        "y": 397.0
      },
      {
        "x": 91.0,
        "y": 396.0
      },
      {
        "x": 93.0,
        "y": 384.0
      },
      {
        "x": 100.0,
        "y": 375.0
      },
      {
        "x": 96.0,
        "y": 397.0
      }
    ],
    [
      {
        "x": 456.0,
        "y": 397.0
      },
      {
        "x": 437.0,
        "y": 392.0
      },
      {
        "x": 450.0,
        "y": 385.0
      },
      {
        "x": 457.0,
        "y": 390.0
      },
      {
        "x": 456.0,
        "y": 397.0
      }
    ]
  ],
  "fibrosis_editable": [
    [
      {
        "x": 204.0,
        "y": 317.0
      },
      {
        "x": 189.0,
        "y": 300.0
      },
      {
        "x": 189.0,
        "y": 274.0
      },
      {
        "x": 196.0,
        "y": 261.0
      },
      {
        "x": 219.0,
        "y": 266.0
      },
      {
        "x": 203.0,
        "y": 284.0
      },
      {
        "x": 203.0,
        "y": 294.0
      },
      {
        "x": 213.0,
        "y": 306.0
      },
      {
        "x": 204.0,
        "y": 317.0
      }
    ],
    [
      {
        "x": 318.0,
        "y": 305.0
      },
      {
        "x": 316.0,
        "y": 299.0
      },
      {
        "x": 318.0,
        "y": 305.0
      }
    ]
  ]
}