{
  "lung_editable": [
    [
      {
        "x": 260.0,
        "y": 287.0
      },
      {
        "x": 253.0,
        "y": 284.0
      },
      {
        "x": 256.0,
        "y": 277.0
      },
      {
        "x": 263.0,
        "y": 280.0
      },
      {
        "x": 260.0,
        "y": 287.0
      }
    ],
    [
      {
        "x": 140.0,
        "y": 367.0
      },
      {
        "x": 138.0,
        "y": 361.0
      },
      {
        "x": 140.0,
        "y": 367.0
      }
    ],
    [
      {
        "x": 98.0,
        "y": 397.0
      },
      {
        "x": 79.0,
        "y": 384.0
      },
      {
        "x": 82.0,
        "y": 375.0
      },
      {
        "x": 92.0,
        "y": 371.0
      },
      {
        "x": 99.0,
        "y": 378.0
      },
      {
        "x": 98.0,
        "y": 397.0
      }
    ],
    [
      {
        "x": 458.0,
        "y": 397.0
      },
      {
        "x": 437.0,
        "y": 392.0
      },
      {
        "x": 464.0,
        "y": 379.0
      },
      {
        "x": 458.0,
        "y": 397.0
      }
    ]
  ],
  "fibrosis_editable": []
}